metaflow_extensions/helloworld/plugins/cards/hello_world_card/__init__.py
metaflow_card-1.0.1.dist-info/LICENSE
metaflow_card-1.0.1.dist-info/METADATA
metaflow_card-1.0.1.dist-info/WHEEL
metaflow_card-1.0.1.dist-info/top_level.txt
metaflow_card-1.0.1.dist-info/RECORD
