Metadata-Version: 2.1
Name: metaflow-card
Version: 1.0.1
Summary: A Hello world metaflow card
Home-page: UNKNOWN
Author: Outerbounds
Author-email: valay@outerbounds.co
License: Apache Software License 2.0
Platform: UNKNOWN
